torch_affine_utils/__init__.py
torch_affine_utils/py.typed
torch_affine_utils/transforms_2d.py
torch_affine_utils/transforms_3d.py
torch_affine_utils/utils.py
torch_affine_utils-0.1.1.dist-info/METADATA
torch_affine_utils-0.1.1.dist-info/WHEEL
torch_affine_utils-0.1.1.dist-info/licenses/LICENSE
torch_affine_utils-0.1.1.dist-info/RECORD
